.gitignore
CHANGES.txt
CONTRIBUTORS.txt
MANIFEST.in
README.rst
setup.py
docs/LICENSE.GPL
docs/LICENSE.txt
src/raptus/__init__.py
src/raptus.multilanguageconstraint.egg-info/PKG-INFO
src/raptus.multilanguageconstraint.egg-info/SOURCES.txt
src/raptus.multilanguageconstraint.egg-info/dependency_links.txt
src/raptus.multilanguageconstraint.egg-info/entry_points.txt
src/raptus.multilanguageconstraint.egg-info/namespace_packages.txt
src/raptus.multilanguageconstraint.egg-info/not-zip-safe
src/raptus.multilanguageconstraint.egg-info/requires.txt
src/raptus.multilanguageconstraint.egg-info/top_level.txt
src/raptus/multilanguageconstraint/__init__.py
src/raptus/multilanguageconstraint/configure.zcml
src/raptus/multilanguageconstraint/extender.py
src/raptus/multilanguageconstraint/index.py
src/raptus/multilanguageconstraint/overrides.zcml
src/raptus/multilanguageconstraint/patches.py
src/raptus/multilanguageconstraint/setuphandlers.py
src/raptus/multilanguageconstraint/vocabulary.py
src/raptus/multilanguageconstraint/browser/__init__.py
src/raptus/multilanguageconstraint/browser/configure.zcml
src/raptus/multilanguageconstraint/browser/foldercontents.py
src/raptus/multilanguageconstraint/browser/notavailable.css
src/raptus/multilanguageconstraint/browser/notavailable.pt
src/raptus/multilanguageconstraint/browser/notavailable.py
src/raptus/multilanguageconstraint/browser/overrides.zcml
src/raptus/multilanguageconstraint/browser/referencebrowser.py
src/raptus/multilanguageconstraint/locales/raptus.multilanguageconstraint.pot
src/raptus/multilanguageconstraint/locales/de/LC_MESSAGES/raptus.multilanguageconstraint.mo
src/raptus/multilanguageconstraint/locales/de/LC_MESSAGES/raptus.multilanguageconstraint.po
src/raptus/multilanguageconstraint/locales/fr/LC_MESSAGES/raptus.multilanguageconstraint.mo
src/raptus/multilanguageconstraint/locales/fr/LC_MESSAGES/raptus.multilanguageconstraint.po
src/raptus/multilanguageconstraint/profiles/default/cssregistry.xml
src/raptus/multilanguageconstraint/profiles/default/metadata.xml
src/raptus/multilanguageconstraint/profiles/default/raptus.multilanguageconstraint_install.txt
src/raptus/multilanguageconstraint/profiles/default/skins.xml
src/raptus/multilanguageconstraint/skins/raptus_multilanguageconstraint/content_status_history.cpt
src/raptus/multilanguageconstraint/skins/raptus_multilanguageconstraint/content_status_history.cpt.metadata
