Metadata-Version: 1.1
Name: raptus.multilanguageconstraint
Version: 1.0a2
Summary: Provides a language selection field on all content objects to display it only in selected languages
Home-page: https://github.com/Raptus/raptus.multilanguageconstraint
Author: Raptus AG
Author-email: dev@raptus.com
License: gpl
Platform: UNKNOWN
Classifier: Programming Language :: Python
